terraform_version/__init__.py
terraform_version/version.py
terraform_version-1.3.0.dist-info/WHEEL
terraform_version-1.3.0.dist-info/METADATA
terraform_version-1.3.0.dist-info/RECORD
