Metadata-Version: 2.1
Name: terraform-version
Version: 1.3.0
Summary: Package for tracking existing Terraform versions
Home-page: https://github.com/joshwycuff/python-terraform-utils/packages/terraform_version
License: MIT
Keywords: terraform
Author: Josh Wycuff
Author-email: Joshua.Wycuff@turner.com
Maintainer: Josh Wycuff
Maintainer-email: Joshua.Wycuff@turner.com
Requires-Python: >=3.6,<4.0
Classifier: License :: OSI Approved :: MIT License
Classifier: Programming Language :: Python :: 3
Classifier: Programming Language :: Python :: 3.10
Classifier: Programming Language :: Python :: 3.6
Classifier: Programming Language :: Python :: 3.7
Classifier: Programming Language :: Python :: 3.8
Classifier: Programming Language :: Python :: 3.9
Project-URL: Documentation, https://github.com/joshwycuff/python-terraform-utils/packages/terraform_version
Project-URL: Repository, https://github.com/joshwycuff/python-terraform-utils
